{
  "english": "English",
  "spanish": "Spanish",
  "french": "French",
  "korean": "Korean",
  "mandarin": "Mandarin",
  "cantonese": "Cantonese",
  "filipino": "Filipino",
  "vietnamese": "Vietnamese",
  "arabic": "Arabic",
  "russian": "Russian",
  "portuguese": "Portuguese",
  "haiti_creole": "Haiti Creole",
  "hindi": "Hindi",
  "german": "German",
  "polish": "Polish",
  "italian": "Italian",
  "urdu": "Urdu",
  "persian": "Persian",
  "telugu": "Telugu",
  "japanese": "Japanese",
  "gujarati": "Gujarati",
  "bengali": "Bengali",
  "tamil": "Tamil",
  "punjabi": "Punjabi",
  "thais": "Thais",
  "lao": "Lao",
  "croatian": "Croatian",
  "bosnian": "Bosnian",
  "montenegrin": "Montenegrin",
  "serbian": "Serbian",
  "armenia": "Armenian",
  "greek": "Greek",
  "hmong": "Hmong",
  "hebrew": "Hebrew",
  "khmer": "Khmer",
  "navajo": "Navajo",
  "oyoruba": "Yoruba",
  "twi": "Twi",
  "igbo": "Igbo",
  "amharic": "Amharic",
  "somali": "Somali",
  "dutch": "Dutch",
  "afrikaans": "Afrikaans",
  "frisian": "Frisian",
  "luxembourgish": "Luxembourgish",
  "scots": "Scots",
  "yiddish": "Yiddish",
  "pennsylvania_dutch": "Pennsylvania Dutch",
  "low_german": "Low German",
  "ilocano": "Ilocano",
  "samoan": "Samoan",
  "hawaiian": "Hawaiian",
  "nepali": "Nepali",
  "marathi": "Marathi",
  "ukranian": "Ukranian",
  "swahili": "Swahili",
  "malayalam": "Malayalam",
  "kannada": "Kannada"
}
